{"sighted_at": "19950216", "reported_at": "19950217", "location": " PawPaw, MI", "shape": "", "duration": "", "description": "Man &amp; wife awakened by immensely loud roaring sound. See 5 bizarre craft hovering nearby in formation!  Good rept..", "airport_name": "Ted Stevens Anchorage International Airport", "airport_distance": 2261.1725726235236, "closest_shooting": 1485.8461088689762, "shootings_in_state": 9, "shootings_per_year": 5, "closest_hospital_name": "Kenai VA Community Based Outpatient Clinic", "closest_hospital_distance": 2167.371109256875, "closest_hospital_region": "VISN 20: Northwest Network", "average_sentiment": -0.4409722222222222, "average_sentiment_confidence": 0.8949989850427333, "most_popular_airline": "US Airways"}
