{"sighted_at": "19950423", "reported_at": "19950423", "location": " Bradenton, FL", "shape": "", "duration": "5 min.", "description": "Man &amp; wife witness &quot;Armada of bright objs,&quot; streak across sky in formation.  Fly SE.  Very unusual.  Not meteors!((NUFORC Note:  No other information provided by witness.  Witness elects to remain anonymous.  PD))", "airport_name": "Sarasota Bradenton International Airport", "airport_distance": 1.6880253361970443, "closest_shooting": 9.000600984106836, "shootings_in_state": 31, "shootings_per_year": 5, "closest_hospital_name": "Sarasota Vet Center", "closest_hospital_distance": 4.629839228678771, "closest_hospital_region": "VISN 8: VA Sunshine Healthcare Network", "average_sentiment": -0.4409722222222222, "average_sentiment_confidence": 0.8949989850427333, "most_popular_airline": "US Airways"}
